{"nodes": [{"id": "quorum_system", "label": "Savant Quorum Multi-Agent Environment", "file_type": "concept", "source_file": "QUORUM.md", "source_location": null, "source_url": null, "captured_at": null, "author": null, "contributor": null}, {"id": "electron_main_spawn_execution_rationale", "label": "Spawn-based Execution Architecture", "file_type": "rationale", "source_file": "QUORUM.md", "source_location": null, "source_url": null, "captured_at": null, "author": null, "contributor": null}], "edges": [], "hyperedges": []}